youtube_downloaders/__init__.py
youtube_downloaders/__main__.py
youtube_downloaders/exception.py
youtube_downloaders/gui.py
youtube_downloaders/options.py
youtube_downloaders/os_operations.py
youtube_downloaders/web.py
youtube_downloaders/youtube.py
youtube_downloaders/__pycache__/__init__.cpython-311.pyc
youtube_downloaders/__pycache__/__main__.cpython-311.pyc
youtube_downloaders/__pycache__/exception.cpython-311.pyc
youtube_downloaders/__pycache__/gui.cpython-311.pyc
youtube_downloaders/__pycache__/options.cpython-311.pyc
youtube_downloaders/__pycache__/os_operations.cpython-311.pyc
youtube_downloaders/__pycache__/web.cpython-311.pyc
youtube_downloaders/__pycache__/youtube.cpython-311.pyc
youtube_downloaders/static/img/youtube.jpg
youtube_downloaders/static/js/script.js
youtube_downloaders/static/styles/style.css
youtube_downloaders/templates/error.html
youtube_downloaders/templates/home.html
youtube_downloaders/templates/youtube.jpg
youtube_downloaders-1.1.2.dist-info/licenses/LICENSE
youtube_downloaders-1.1.2.dist-info/METADATA
youtube_downloaders-1.1.2.dist-info/WHEEL
youtube_downloaders-1.1.2.dist-info/entry_points.txt
youtube_downloaders-1.1.2.dist-info/top_level.txt
youtube_downloaders-1.1.2.dist-info/RECORD
