Metadata-Version: 2.4
Name: youtube_downloaders
Version: 1.1.2
Summary: Package to download youtube videos and playlist
Author-email: Ishan Mahajan <imahajan0007@gmail.com>
Project-URL: Homepage, https://github.com/ishan65/youtube_download
Classifier: Programming Language :: Python :: 3
Classifier: License :: OSI Approved :: MIT License
Requires-Python: >=3.10
License-File: LICENSE
Requires-Dist: Flask==3.0.0
Requires-Dist: pytubefix
Requires-Dist: importlib-metadata; python_version >= "3.10"
Dynamic: license-file
